docs_validation/src/__init__.py
docs_validation/src/__main__.py
docs_validation/src/base.py
docs_validation/src/cli.py
docs_validation/src/config.py
docs_validation/src/engine.py
docs_validation/src/models.py
docs_validation/src/reporters/__init__.py
docs_validation/src/reporters/markdown_reporter.py
docs_validation/src/validators/__init__.py
docs_validation/src/validators/code_execution.py
docs_validation/src/validators/code_linting.py
docs_validation/src/validators/code_typing.py
docs_validation/src/validators/cross_references.py
docs_validation/src/validators/external_links.py
docs_validation/src/validators/financial.py
docs_validation/src/validators/markdown.py
docs_validation/src/validators/python.py
docs_validation/src/validators/sdk_methods.py
docs_validation/src/validators/security.py
fivetwenty/__init__.py
fivetwenty/client.py
fivetwenty/configuration.py
fivetwenty/exceptions.py
fivetwenty/py.typed
fivetwenty/_internal/__init__.py
fivetwenty/_internal/environment.py
fivetwenty/_internal/utils.py
fivetwenty/endpoints/__init__.py
fivetwenty/endpoints/accounts.py
fivetwenty/endpoints/instruments.py
fivetwenty/endpoints/orders.py
fivetwenty/endpoints/positions.py
fivetwenty/endpoints/pricing.py
fivetwenty/endpoints/trades.py
fivetwenty/endpoints/transactions.py
fivetwenty/models/__init__.py
fivetwenty/models/accounts.py
fivetwenty/models/base.py
fivetwenty/models/enums.py
fivetwenty/models/error_codes.py
fivetwenty/models/error_details.py
fivetwenty/models/instruments.py
fivetwenty/models/orders.py
fivetwenty/models/positions.py
fivetwenty/models/pricing.py
fivetwenty/models/streaming.py
fivetwenty/models/trades.py
fivetwenty/models/transactions.py
fivetwenty-0.3.0.dist-info/licenses/LICENSE
fivetwenty-0.3.0.dist-info/METADATA
fivetwenty-0.3.0.dist-info/WHEEL
fivetwenty-0.3.0.dist-info/top_level.txt
fivetwenty-0.3.0.dist-info/RECORD
