Metadata-Version: 2.4
Name: fivetwenty
Version: 0.3.0
Summary: Simple, elegant Python client for OANDA's REST API v20
Author: FiveTwenty Contributors
License: MIT
Project-URL: Homepage, https://nimbleox.github.io/fivetwenty/
Project-URL: Repository, https://github.com/NimbleOx/fivetwenty
Project-URL: Documentation, https://nimbleox.github.io/fivetwenty/
Project-URL: Bug Reports, https://github.com/NimbleOx/fivetwenty/issues
Keywords: oanda,trading,forex,api,finance
Classifier: Development Status :: 4 - Beta
Classifier: Intended Audience :: Developers
Classifier: Intended Audience :: Financial and Insurance Industry
Classifier: License :: OSI Approved :: MIT License
Classifier: Programming Language :: Python :: 3.10
Classifier: Programming Language :: Python :: 3.11
Classifier: Programming Language :: Python :: 3.12
Classifier: Programming Language :: Python :: 3.13
Classifier: Topic :: Office/Business :: Financial
Requires-Python: >=3.10
License-File: LICENSE
Requires-Dist: httpx>=0.25.0
Requires-Dist: pydantic>=2.5.0
Dynamic: license-file
